setup.py
cdbclient/__init__.py
cdbclient/auth_plugin.py
cdbclient/base.py
cdbclient/cdb_cmd.py
cdbclient/client.py
cdbclient/common.py
cdbclient/exceptions.py
cdbclient/extension.py
cdbclient/novaclient.py
cdbclient/service_catalog.py
cdbclient/shell.py
cdbclient/utils.py
cdbclient.egg-info/PKG-INFO
cdbclient.egg-info/SOURCES.txt
cdbclient.egg-info/dependency_links.txt
cdbclient.egg-info/entry_points.txt
cdbclient.egg-info/requires.txt
cdbclient.egg-info/top_level.txt
cdbclient/openstack/__init__.py
cdbclient/openstack/common/__init__.py
cdbclient/openstack/common/gettextutils.py
cdbclient/openstack/common/importutils.py
cdbclient/openstack/common/strutils.py
cdbclient/openstack/common/apiclient/__init__.py
cdbclient/openstack/common/apiclient/auth.py
cdbclient/openstack/common/apiclient/base.py
cdbclient/openstack/common/apiclient/client.py
cdbclient/openstack/common/apiclient/exceptions.py
cdbclient/openstack/common/apiclient/fake_client.py
cdbclient/v1/__init__.py
cdbclient/v1/backups.py
cdbclient/v1/config_parameters.py
cdbclient/v1/configurations.py
cdbclient/v1/databases.py
cdbclient/v1/datastore_versions.py
cdbclient/v1/datastores.py
cdbclient/v1/flavors.py
cdbclient/v1/ha.py
cdbclient/v1/instances.py
cdbclient/v1/limits.py
cdbclient/v1/root.py
cdbclient/v1/schedules.py
cdbclient/v1/users.py
cdbclient/v1/versions.py