Metadata-Version: 1.1
Name: cdbclient
Version: 1.0.4
Summary: Rich client bindings for the Rackspace Cloud Database REST API.
Home-page: http://www.rackspace.com/cloud/databases
Author: Rackspace
Author-email: UNKNOWN
License: Apache License, Version 2.0
Platform: UNKNOWN
Classifier: Development Status :: 5 - Production/Stable
Classifier: Environment :: Console
Classifier: Intended Audience :: Developers
Classifier: Intended Audience :: Information Technology
Classifier: License :: OSI Approved :: Apache Software License
Classifier: Operating System :: OS Independent
Classifier: Programming Language :: Python
